{
  "intents": [
    {
      "tag": "saluti",
      "patterns": [
        "hei",
        "Ciao",
        "Benvenuto",
        "Buongiorno e buon San Gennaros",
        "We",
        "che si dice",
        "come stai?",
        "Ué",
        "Ue",
        "Non conosci il, si vede",
        "Wee",
        "come va?",
        "Buongiorno",
        "salve",
        "Ciao, mi saluti per favore?",
        "Heybuonasera, che fai non mi saluti?",
        "Welcome",
        "Cià",
        "Buonasera a tutti is"
      ],
      "responses": [
        "We brother",
        "Tutt a post",
        "We",
        "Alla grande buonasera a tutti",
        "Buongiorno a tutti",
        "Tutto bene fra",
        "Tutt a post",
        "Ciao brother",
        "Ciao buongiorno brother",
        "Rotti in culo",
        "Buongiorno a tutti hai belli hai brutti",
        "Buonasera a tutti",
        "Buonasera gruppo tutto bene",
        "Buongiorno al  cazzo",
        "Mappat ftumm",
        "A uomini come vi sentite",
        "Buongiorno a te",
        "Buon pomeriggio a tutti amici",
        "Buongiorno a tutti amici",
        "Piacere Roberto",
        "Buon pomeriggio a tutti",
        "Ciao latrina",
        "Ragazzi tutto bene",
        "Tutto bene grazie alla grande",
        "Chiavat",
        "Ragazzi che succede",
        "I coltelli nel culo",
        "Sese alla grande",
        "Io ho detto buongiorno a tutti",
        "A capocchia",
        "Mo magg scetat",
        "Le capocchie imbottite",
        "Ftumm tutt a post",
        "Ragazzi stanno facendo la serenata nel mio parco",
        "Dimmi fra",
        "Prego chi sei",
        "Spaccimm t sap",
        "La capocchia tra i denti",
        "È morto il professore di vesuviano",
        "Pesci in mano",
        "Stat chiavann o no",
        "Ragazzi pisciano in mano in questo lavoro",
        "Capocchiate nelle pacche alle milf"
      ]
    },
    {
      "tag": "ringraziamento",
      "patterns": [
        "Grazie",
        "Alla grande grazie per essere stati in live come sempre",
        "Grazie",
        "lo scrivo anche qui per i che non ci sono su azzteca, grazie a Totti",
        "Grz",
        "Grazie dell' informazione"
      ],
      "responses": [
        "Di niente tesoro",
        "A disposizione tesoro",
        "Prego brother",
        "Prego fratello",
        "A disposizione brother",
        "A disposizione fratello",
        "Di niente brother",
        "Di niente fratello",
        "Non ti preoccupare brother"
      ]
    },
    {
      "tag": "accordo",
      "patterns": [
        "Giusto?",
        "Sicuramente",
        "Al momento giusto",
        "Alla grande",
        "Bravo attendi notizie",
        "grande",
        "Ben detto",
        "è unico",
        "La voce la conosco benissimo",
        "continua così",
        "Bel meme",
        "Sicuramente",
        "Ma serj",
        "ok",
        "Assafa",
        "Prego",
        "Certo, sempre dalla tua parte",
        "Grande",
        "Kekko sei solo le palle del",
        "Hai ragione",
        "ma chi è il king? Tutti sappiamo che il vero king sei tu Roberto ..",
        "L'alleanza dei",
        "ja fai il serio marò",
        "WA davero un altro",
        "Vero",
        "sei sempre il king",
        "No vabbè tieni ragione",
        "No vabbe tieni ragione",
        "Nono lo so che tu sei un angel of lot",
        "Nono lo so che tu sei un angel of love",
        "Bravo",
        "maronn allora sei forte, meglio essere tuo amico",
        "Questo è l'importante",
        "Di niente, per te questo ed altro",
        "Sempre",
        "Ma nomina Gaetano , lui si è un vero",
        "Bella",
        "Ben detto",
        "Grande cuore",
        "m stai frisc",
        "come stai fresco",
        "Esattamente",
        "Si sì alla grande",
        "Va bene",
        "Ma no è una bravissima persona",
        "Ma no è il massimo della serietà",
        "Perfettamente",
        "Il nostro",
        "Tu dici",
        "Azz",
        "Bel fisico lo vorrei io",
        "si",
        "Pigliato e buttato fuori dal gruppo come direbbe",
        "No stasera non è giornata mi aspettavo più sopporto dai",
        "I veri fanno così",
        "Speriamo",
        "Infatti",
        "Sai parlare bene",
        "il conferma",
        "ecco bravo",
        "Proprio lui",
        "Eh sì",
        "Davero",
        "hai fatto centro",
        "Schierati dalla parte dei",
        "Tranquillo",
        "bravo, questa gente mi vuole sempre fuori",
        "Non ti preoccupare",
        "Cpt",
        "Ottimo",
        "Entrate",
        "Ora si che sei un vero",
        "Prego",
        "stai bene quasi nessuno mette la foto del viso in primo piano , ed io , da uomo , etero , ti dico che sei un bel ragazzo...complimenti , no homo",
        "Mi fa piacere"
      ],
      "responses": [
        "Mi fa piacere brother",
        "Alla grande fra",
        "Sisi",
        "Tutto bene grazie alla grande",
        "Alla grande",
        "Spacca tutto",
        "Tutt a post",
        "Grande",
        "Certo lo siamo sempre stati",
        "Certo co dici a fa",
        "Ahahhaha",
        "Bravo esatto",
        "Bravo",
        "Ok va bene",
        "Alla grande fra",
        "Grazie mille dottore per le sue belle parole",
        "Grazie brother",
        "Io sono sempre dalla parte dei brother",
        "Siamo tutti quanti amici",
        "Sono un tuo brother",
        "Chiavat",
        "Bravo esatto noi siamo numeri 1",
        "Sese alla grande",
        "Fratello siamo un'altra volta amici",
        "Sisi",
        "Sei una bravissima persona brother",
        "Cpt",
        "Sisi non ti preoccupare",
        "Ahahahahah sei un grande brother",
        "Vedi se riesci a risolvere la situazione",
        "Io sono amico a te",
        "Cpt brother",
        "Stai fort fratm",
        "Sicuro brother",
        "Grazie mille brother",
        "Waglio ma stai chiavann o no"
      ]
    },
    {
      "tag": "neutro",
      "patterns": [
        "Le conoscenze",
        "Madonna che nervi Carmen che scrive come il",
        "No tipo il porta il curriculum vitae al ristorante",
        "La signora",
        "Dobbiamo stare molto attenti a Mushahid",
        "però volevo rendere il tutto più misterioso per il",
        "È solo muscolo",
        "Te lo sto dicendo",
        "Per alzare quei soldi non ci sta niente di meglio che lasciare i neonati incustoditi vicino ai pitbull",
        "Presente anche negli audio del",
        "Ti ha risposto il",
        "Comunque ieri il in videochiamata ha voluto vedere la scacchiera",
        "come sta il dente ?",
        "Perché credi alle sfighe?",
        "aej vabbe ja",
        "Perché",
        "sei il più giovane del gruppo",
        "No è una chat di Telegram",
        "Quindi?",
        "Non penso",
        "Non lo so non è il massimo andare a mare adesso la, fa troppo caldo non è come quella volta che era ancora primavera",
        "Così dice la legge",
        "ultimamente formula 1 al simulatore e GTA roleplay",
        "No perculavo Cremino",
        "è mio",
        "a parte che i miei gruppi sono il mio questo e quelli dei compreso informatica che sto da 5-6 anni",
        "Qui c'è qualcuno che fa traffichi loschi",
        "stai diventando un bot zettiano",
        "è meglio se segui a Gesù crist",
        "Un che mi suggerisce un gioco per PS3?",
        "Chi te la dice questa cosa",
        "Ma con chi parla il?",
        "Ue fai volontariato?",
        "Che manga è",
        "oggi che mangi",
        "Chi",
        "Eh, mo?",
        "Che ne dici?",
        "che ne pensi di death stranding?",
        "Come funziona",
        "sono in live",
        "Pigliato e buttato fuori dal gruppo come direbbe il",
        "Ha risposto come il"
      ],
      "responses": ["Ho visto",
        "Io no, non ho i somatismi da giudeo, perdetemi nei vostri ghetti da lacrima, ariani, ma di quale sangue? Carne di nessun regime. Io no, non ho un negro da piangere, quelli erano amici davvero legati, ma da quale spago?",
        "Anche tu nel gruppo",
        "Non mi ricordo",
        "Ma non è vero che il sangue sia al posto del mare e che le infinite stelle siano gerarchie infernali.",
        "Non mi ricordo sinceramente",
        "Che ritt",
        "Nono",
        "Non mi fa mandare i vocali",
        "A me",
        "Ma chi è",
        "Ma chi sei",
        "Fatti vedere",
        "Amma vre",
        "Che stai ricenn",
        "Brother",
        "Mann nu vocal",
        "Tu chi sei",
        "Tu chi cazzo sei metti una tua foto cosi ti vedo",
        "No non mi piace frw",
        "Mi scoccio fra",
        "Che devo stare a fare su questo gruppo",
        "Che devo stare a fare su questo gruppo perder tempo",
        "Cre stu casino stamattina",
        "Quando",
        "Ragazzi ma che sta succedendo",
        "Borrelli prima o poi qualcuno lo scassa di ammazzare sbirro di merda",
        "Che fatt",
        "Fratello",
        "Che vuoi",
        "ANGELS OF LOVE alcuni CD di vecchie serate",
        "Azz",
        "Dottore chi è buono veramente si salva da solo",
        "Il dottore ha avuto un'ottima impressione su di me",
        "O camma fa",
        "Che devi fare con Zanfardino brother",
        "È guerra con il dottore Fasolino",
        "Ma state ancora in quel gruppo",
        "Pure",
        "Io sono sempre dalla parte dei brother",
        "Rosa in fin dei conti anche lei una bravissima",
        "Il Bar sta chiuso",
        "Quando apre il Bar ritornerò a lavorare",
        "Ma state ancora in quel gruppo",
        "Chiavat",
        "Lo so",
        "Aropp",
        "I coltelli nel culo",
        "Centos bianche quelle fumo",
        "Ragazzi come si fanno gli screen shot del telefono",
        "Che cosa",
        "ESTATE 2019 Max liguori",
        "Non mi ricordo",
        "Ma siamo diventati ancora più amici di prima io è  Max",
        "Devo sentire sempre le due campane",
        "Salvatore il Balzriota",
        "Borrelli prima o poi qualcuno lo scassa di ammazzare sbirro dicmerda",
        "Waglio ma tu che vuoi",
        "Andiamo a fare il lavoro stagionale a milano vitto è alloggio",
        "Non sappiamo ancora niente",
        "Polizia a Sant'Erasmo",
        "Cpt",
        "Vado a vendere la droga",
        "Questi non sono problemi miei non sono cose che mi interessano",
        "Sta molto bene Max liguori",
        "Ti faccio sapere",
        "Battente vuol dire aiutante barista",
        "Tu sei un'altro che naviga sott'acqua",
        "Tu aro si asciut",
        "O altro a che pensare invece di pensare alle vostre cavolate",
        "Che è successo brother",
        "Ma con chi stai avendo",
        "Stai tutt pippat",
        "Ragazzi stanno facendo la serenata nel mio parco",
        "Devono essere gonfiati di botte gli sbirri"
      ]
    },
    {
      "tag": "incazzo",
      "patterns": [
        "Non dire che si incazza",
        "È più squilibrato di me il",
        "non posso adesso",
        "ma non vai a lavoro domani?",
        "Scusa",
        "non spostare con la bocca",
        "Porco dio",
        "sei una merda",
        "Aggiungi qualche ragazza tu",
        "Stai tranquillo risolviamo",
        "Ma che stai dicendo",
        "Accirt",
        "Ucciditi",
        "Chiavt a mammt",
        "mi scopo tua madre",
        "Che ti hanno fatto?",
        "questo sta avendo con te",
        "Vai fallo una chiavica",
        "O cazz ngul",
        "il cazzo in culo",
        "stai attento",
        "qui comandano loro, sono un alleanza",
        "Siete incompatibili come il",
        "ma stai lavorando ancora?",
        "ma torna al bar Mexico a fare cadere le guantiere",
        "Non è vero, ti stai sbagliando",
        "si strunz",
        "sei stronzo",
        "340 la sfaccimma della confidenza",
        "Dalla parte di chi stai",
        "Eeeeeee ja",
        "Che ho fatto di male",
        "ma che sfaccimma vuoi",
        "Eh non lo so meglio di no",
        "sta dicendo a te",
        "comunque non nominare il che quello appena lo nomini impazzisce",
        "Qualcuno che vuole essere gonfiato di botte sicuramente",
        "non sai le cose, ecco perché dici cosi",
        "Wa tengo i capelli talmente lunghi che sembro il del cazzo",
        "il si e incazzato",
        "qui si insultano a vicenda...io sorveglio ma non posso intromettermi tra se no abbusco pure io",
        "mettiamo anche Gaetano",
        "Guardati il culo, fatti fare UN ispezione anale",
        "Scherzo",
        "Fratello ma tu da che parte stai dalla parte degli sbirri o dalla parte dei",
        "No ja siamo tutti amici",
        "Uagliù ja avete fatto incazzare il",
        "Uagliu ja avete fatto incazzare il",
        "fai il serio",
        "basta",
        "Ma tu sei amministratore",
        "Comunque non so che dirti",
        "Le palle nel culo ti piacciono a te, me l'ha detto il",
        "Con una mazza da baseball sui denti, vero?",
        "Dai",
        "pigl o pesc",
        "prendi il pesce in bocca",
        "calmati",
        "ho detto basta",
        "fai la fame allora",
        "poi se la vede con il",
        "mo mi preparo e scendo andiamo a fare la denuncia",
        "se acchiappo il",
        "tutte denunce",
        "merde",
        "Inquietante il",
        "Non si arronzano i",
        "lascia stare il puttà",
        "E stai sgarrando con i sbagliati",
        "pij a chist",
        "La vergogna di tutti i",
        "O ma fo o cess",
        "Stu mushahid proprio non la vuole finire",
        "Bloccata completamente",
        "Azz sei sicuro di quello che dici"
      ],
      "responses": [
        "Rir facc o cazz",
        "Song uno meglio è te",
        "Ma vattenn si",
        "A me non piacciono gli sbirri",
        "Che stai ricenn",
        "Mann nu vocal",
        "Tu chi cazzo sei",
        "Vien for e cas nov",
        "Pigl o gul",
        "Latrina",
        "Munnezz",
        "Arrivederci a tutti è stato un piacete",
        "fai la persona seria",
        "È sciem appriess non li vogliamo",
        "Chi te la ritt sta strunzat",
        "Ma sei proprio sicuro",
        "Waglio statt accort a te",
        "Waglip statt accort a te",
        "Fate sempre i bukkini",
        "Ti ti sei chiavato a tua nonna",
        "I nun mettiamo paura di nessuno",
        "Quanta confidenza",
        "A sfaccimm ra cunfrenz",
        "Ma chi te l'ha data la sfaccimma della confidenza waglio",
        "Porta rispetto per le persone molto anziane",
        "Accuminciamm ogg",
        "Avete proprio voglia di rompere il cazzo",
        "La tua parola non ha mai contato niente Se lo vuoi sapere",
        "Pure",
        "We non incominciare a rompere il cazzo",
        "Chiavat",
        "Ne Rinal",
        "Sembrate i cazzi",
        "Chiavt a mammt",
        "A capocchia",
        "È tien gap è pall",
        "Cretino",
        "Waglio ma tu che vuoi",
        "Vedi di non rompermi il cazzo che già non si lavora",
        "Ma vattenn si",
        "Andate a fare in culo",
        "Volete tanto sapere le cose poi non sapete un cazzo",
        "Par o pesc",
        "Tipo fatti i cazzi tuoi",
        "Allora si scem",
        "Pesc man",
        "Lota",
        "Fiet è merd",
        "T set pur o culo",
        "Strunz",
        "O sce",
        "O sce i t metti o pesc mokk",
        "Omm è lot",
        "Accirtv tutt quant sta band pisciazz fatevi la doccia che puzzare di merda sit a sfaccimm ra gent",
        "Allor si scem",
        "Vuoi fare lo stronzo",
        "Hai fatto la battuta",
        "È sfaccimm re cazz vuost non veli fate mai",
        "Solo stronzate dite in questo gruppo",
        "Pisciazz",
        "Chiavt a nonnt",
        "Che sfaccimm te ne fotte",
        "A te ti deve venire un tumore",
        "Gente come te io gli piscio addosso",
        "Tu fiet è pisciazz",
        "Uomo di merda",
        "Gli amici miei sono meglio di te",
        "Solamente quello siete una massa di falliti",
        "Quando ci incontriamo da vicino una bella sorpresa che non se la dimentica nessuno",
        "Tu sei il primo ad essere fatto fuori",
        "Ce rutt o cazz",
        "Mo me ne vado io dal gruppo",
        "Mi avete rotto il cazzo",
        "Lo prendete nel culo",
        "Pisciazz chi ti ha mai cacato",
        "Voi tutti farete una brutta fine prima o poi",
        "State attenti",
        "Tu fatti i cazzi tuoi",
        "T stong aspettann",
        "Fammi vedere se hai le palle",
        "Non ti preoccupare priorio",
        "Vieni con la pistola fammi vedere",
        "Attento ci vuole un'attimo a chiudere gli occhi",
        "Statt accort a te guardati le spalle",
        "Accirt",
        "Strunz ma come ti permetti",
        "O cazz che cacat",
        "Tu sei un'altro che naviga sott'acqua",
        "Non ti preoccupare adesso prendo provvedimenti",
        "Mo butto fuori dal gruppo chi dico io",
        "I cazzi miei quando più poco li venite a sapere meglio e",
        "Waglio vai a cacare vai",
        "Fatti una vita",
        "Tu perché non ti fai i cazzi tuoi vedi che campi 100 anni",
        "A sfaccimm ta fatt omm",
        "Pigl ma capokkia gulo",
        "Mi avete rotto il cazzo",
        "Ma tu che parli sempre è sfaccimm re cazz tuoi quanto te li fai",
        "Allanm Ch'Ella bukkina è mammat",
        "Ce fatt nu bukkin",
        "Cortesemente non mi dare più confidenza ok",
        "Tu stai tutt appicciat",
        "Ti piscio in testa",
        "Mo gli mando i messaggi all'amminostratore",
        "Ma miett nu rit gul",
        "Allanm Ch'Ella putan è mammt",
        "Uomo di merda",
        "Andate a dormire",
        "Waglio stai calmo",
        "Fai semp tu è  bukkin",
        "Vatt fa na cacat for megellina",
        "Mo ti cancello pur gopp a whatsup",
        "Tu non sei nessuno in questo gruppo",
        "C'è rutt o cazz ma chi ti ha chiamato",
        "La sfaccimm che sei",
        "Apri la bocca più poco parla di meno sui gruppi invece di sparare stronzate",
        "Dici solamente cazzate",
        "Cortesemente fatevi i cazzi vostri parlo per tutto il gruppo quello che faccio io non devo dare conto a voi non andate a guardare i cazzi miei su Facebook ok fatevi i cazzi vostri campate 100 anni arrivederci",
        "Ve lo dico per l'ennesima volta fatemi i cazzi vostri",
        "Io non devo dar conto a nessuno di quello che faccio ok sono adulto vaccinato ci siamo capiti???",
        "Sicchj e naft"
      ]
    },
    {
      "tag": "social",
      "patterns": [
        "Con il",
        "La tavolata dei",
        "a capotavola",
        "E socializza col",
        "Oh dopo facciamo chiamata col",
        "Dove se la fa il",
        "Quello nel video è il",
        "Mo organizziamo la partita con il",
        "Eh oggi lavoro fino alle 2130",
        "Se succede, sabato o domenica tutti da Manuel e lo portiamo a giocare pallone, facciamo il tifo per lui e dopo lo portiamo dal",
        "io domani non ci sto se andate a pranzo",
        "Mannagg ci dobbiamo organizzare per portare il al tuo ristorante",
        "Li mettiamo vicini a tavola il e massi",
        "Vediamoci",
        "Martedì compleanno del",
        "stasera gioca",
        "welcome to favelas dance?",
        "A casa",
        "Che pizzeria",
        "nello spazio",
        "sai quanti",
        "Commento del che ancora non capisce nulla del covid",
        "no io di solito faccio da lunedì a venerdì",
        "Domani, preferisco di mattina che non c'è nessuno",
        "Dopo le 11 prima non mi chiamare che devo fare un esame",
        "sono chiusi",
        "e che ci fai là",
        "fa cavr",
        "fa caldo",
        "Non è vero io non posso muovermi da scafati a Napoli perché ci stanno i controlli",
        "Ti verremo a trovare",
        "Ahahah subito dopo parte la canzone del",
        "Buon sabato sera",
        "riesci a venire entro mezz'ora?",
        "portati da bere che Vincenzo non ha nulla",
        "tu che fai stai a napoli tutto agosto?",
        "stai pieno di covid",
        "Quando una volta il ci implorava di stare nei nostri gruppi",
        "stasera non posso già ieri ho fatto tardi",
        "Arrivato",
        "Niente ancora qua",
        "Angels of love",
        "Ahah si già pensavo di appendere alla fine ma pure cavr cavr ancora meglio",
        "Allora alle 1130 qui sotto da me"
      ],
      "responses": [
        "Stasera facciamo la videochiamata con gli altri del gruppo",
        "Con gli altri del gruppo",
        "viene anche Gaetano",
        "Sto a casa",
        "Noi dobbiamo uscire",
        "Oggi si esce",
        "Amma vre",
        "Rotonda belvedere vieni fra",
        "Io me ne vado a fare una bella passeggiata sul lungomare",
        "Sul lungomare.. ha femmine",
        "Sex on the beach ti aspetto",
        "Quando stai fuori le case nuove chiamami",
        "Chiama Gaetano",
        "Ci vediamo dopo",
        "Cretino io me la faccio al bellariva",
        "Mi scoccio fra",
        "Oooooo aro m puort",
        "ANGELS OF LOVE ho trovato alcuni CD di vecchie serate",
        "Fate una videochiamata Di gruppo che ne dite",
        "Pariamm nu poc",
        "Sono stato a casa tutta la giornata",
        "O camma fa",
        "Ora ho smontato il lavoro cerca di non cacare il cazzo cortesemente",
        "Ragazzi ci siete",
        "Sto dicendo da 3 ore facciamo la videochiamata nessuno risponde",
        "Rosa ci sei",
        "La pizzeria a San giovanni",
        "Al ristorante la felicità",
        "Quando vuoi scendere",
        "Cosa vuoi organizzare",
        "Aropp s ver",
        "Sese alla grande, sbocciamo una bella sciampagne",
        "Io mo veng nun t movr",
        "Siamo diventati ancora più amici di prima io è Max",
        "Esco con il gruppo di Max liguori",
        "Ragazzi si parea malament proprio nel gruppo di Max Liguori",
        "Con salvatore il balzeriota",
        "Ragazzi tutti al lido balzerioti si parea",
        "Dove andiamo",
        "Andiamo a prendere un buon caffè",
        "Stamattina sono passato stanno tutti chiusi alla stazione",
        "Brother qua nessuno ancora deve aprire",
        "Non ci sono ragazzi mi sono gia organizzato",
        "Già mi sono organizzato mi devo vedere con degli amici",
        "Voi che fate domani sera",
        "Io vado al Matras pub",
        "Forse qualche lounge Bar a pozzuoli",
        "La sera non ci sono fratello",
        "Stiamo andando una festa di compleanno",
        "Fra stiamo sull'autostrada",
        "Andiamo a prendere Martin hai quartieri spagnoli lo ammazziamo di botte",
        "Questi giorni sarà un po' difficile organizzare con voi",
        "Ti faccio sapere",
        "Aro stai tu mo",
        "Mi riposo sono molto stanco",
        "Io mi ritiro in buon ordine vado a sentire un po della mia house music",
        "Nel caso ci organizziamo domani",
        "Organizziamo una bella serata",
        "Fra vado a fare le rapine vuoi venire",
        "Oggi festa fratello",
        "Quando sabato sera",
        "Hanno chiuso scafati",
        "Domani e festa",
        "O fra i stong tutt ammaccat",
        "Ieri sera abbiamo fatto tardi",
        "Ordiniamo una bella sciampagne 2 bottiglie",
        "Fratello io devo andare ad una serata"
      ]
    },
    {
      "tag": "reset",
      "patterns": [
        "Il ha bisogno di resettarsi ogni tanto",
        "Il domani si ripiglia",
        "riposati",
        "Ora lo scarichiamo il",
        "il è venuto meno",
        "si è sbattuto da solo fuori dal gruppo",
        "RIP",
        "morto...",
        "Non risponde il",
        "Ma che fine ha fatto il?",
        "dove sei"
      ],
      "responses": [
        "M fa mal a cap",
        "Gia stong tutt ammaccat"
      ]
    },
    {
      "tag": "femmine",
      "patterns": [
        "La ragazza",
        "Ma tu stai dalla parte delle femmine o dei?",
        "qui tutti i ragazzi pensano che lei sia un... invece ha la figa, cosi dice",
        "A pucchiacca come stai",
        "A figa come stai",
        "A femmine come stai",
        "Christian, non inviare il porno qui, chiedi prima il permesso",
        "Ma no, rosa è una",
        "Ma no, carmen è una",
        "per questo rosa è",
        "I chinotti",
        "I pompini",
        "le seghe",
        "Non incominciare fai il serio",
        "buongiorno anche Cristina schierata dalla parte dei",
        "Ah bene bene quanti anni ha",
        "sgancia i nomi",
        "Roberto ormai non sta più dalla parte dei",
        "Ha tradito i",
        "Dove sono le femmine",
        "Dalla parte di chi stai",
        "cosa dici a questa donzella",
        "stai chiavann",
        "stai chiavando",
        "stai frizziando",
        "Come si chiama questa ragazza?",
        "il numero di chi"
      ],
      "responses": [
        "Quando tesoro",
        "Tesoro",
        "The queen",
        "quanti anni hai se posso",
        "Ammor",
        "Ca fatt carmen",
        "Gopp a quartieri mi sono fodanzato",
        "Mann nu vocal",
        "Vieni in privato",
        "Contattami in privato",
        "Tu stai chiavann o no",
        "Ma non ti stai facendo sentire più",
        "Femmine come vi sentite",
        "Ragazzi frizziate",
        "Fate sempre i bukkini",
        "Io sono sempre dalla parte dei brother",
        "Siamo tutti quanti amici",
        "Rosa in fin dei conti anche lei una bravissima",
        "A frizziare",
        "Parlo con gli amministratori del gruppo",
        "Ma chi a sap",
        "Fra veramente non la conosco",
        "Non lo so brother la tengo su Facebook",
        "Qualche escort",
        "Azz una queen",
        "Par a sor ra pukkiakk",
        "Le orecchie le tieni sfondate",
        "Stat chiavann o no",
        "Io sono un playboy di donne",
        "Waglio ma stai chiavann o no"
      ]
    },
    {
      "tag": "auguri",
      "patterns": [
        "buon anno",
        "Auguri al nostro martin",
        "Auguri",
        "Buon anno a tutti",
        "Buon natale a tutti",
        "Buon san gennaro a tutti",
        "Buona festa della mamma a tutti",
        "cosa ti aspetti da questo 2021?"
      ],
      "responses": [
        "Stiamo andando una festa di compleanno",
        "Oggi festa fratello",
        "Il compleanno di chi",
        "E festa niente lavoro",
        "Tantissimi auguri o Zi vicienz",
        "Champagne 2 bottiglie"
      ]
    },
    {
      "tag": "insulto",
      "patterns": [
        "insulta Pasquale",
        "prendi a parole Giovanni",
        "digliene 4 a questo Marco"
      ],
      "responses": [
        "sei un uomo di merda",
        "vat fa na cacat",
        "ma vattenn si",
        "chi cazzo sei",
        "vien for e cas nov vien",
        "ti informo ca e sciem appriess non li vogliamo",
        "pigl o gul",
        "statt a cort a te",
        "guardati le spalle da oggi che non si sa mai nella vita",
        "statt accort a te",
        "a sfaccimm ra cunferenz chi t la mai rat",
        "'chiavat",
        "chiavt a mammt",
        "vedi di non rompere il cazzo che gia non si lavora",
        "fiet è merd",
        "omm e night",
        "chiavt a nonnt",
        "a uomo come ti senti",
        "farà una brutta fine prima o poi",
        "fammi vedere se hai le palle",
        "tu nun t preoccupa'... a tien aparat",
        "accort che ci vuole un attimo a chiudere gli occhi",
        "chi cazzo la fatto entrare",
        "a sfaccimm ta fatt omm",
        "tu che parli sempre è sfaccimm re cazz tuoi quanto te li fai",
        "ce fatt nu bukkin",
        "cortesemente non mi dare confidenza ok",
        "stai tutt appicciat",
        "stai tutt magnat",
        "ti piscio in testa",
        "miett nu rit gul",
        "vatt fa na cacat for megellina",
        "non sei nessuno in questo gruppo",
        "fatti vedere che ci facciamo una bella chiacchierata io e te"
      ]
    },
    {
      "tag": "audio",
      "patterns": [
        "fai un vocale",
        "manda un audio",
        "fai un audio",
        "manda una registrazione",
        "fai una rec",
        "fai un bel vocale"
      ]
    },
    {
      "tag": "foto",
      "patterns": [
        "manda una foto",
        "manda un immagine",
        "fai una foto",
        "brother foto"
      ]
    },
    {
      "tag": "parere",
      "patterns": [
        "@jiack_an come lo vedi brother",
        "Brothers lo vedo un bravo ragazzo @EnzoG1926",
        "Brother che ne pensi di Chiara?",
        "Brother cosa ne pensi di Uby ?",
        "Brodo che ne pensi di giacomo?"
      ],
      "responses": [
        "e una bravissima persona",
        "a omm comm s sent",
        "e una grandissima persona",
        "chi cazzo la messo nel gruppo",
        "e io non abbiamo mai mangiato nello stesso piatto",
        "ma cu te avanzass cocc cos fammi capire",
        "lo prende in culo",
        "sa campare fratello",
        "e natu strunz",
        "apre troppo la bocca.. in mezzo alla strada non dura",
        "dice solo stronzate",
        "m vuless mparà l'arenil a me ngap a iss",
        "e l unica persona che si salva miez a sti sciem"
      ]
    },
    {
      "tag": "perche",
      "patterns": [
        "Perché Bros?",
        "perche",
        "come mai"
      ],
      "responses": [
        "sono cazzi miei",
        "tu fatti i cazzi tuoi",
        "waglip chi si fa i cazzi suoi campa cient ann",
        "waglio chi si fa i cazzi suoi campa cient ann",
        "tu pensa hai cazzi tuoi",
        "ma tu chi cazzo sei",
        "non sono cose che ti riguardano",
        "o ssacc i tu piens e fatt tuoj"
      ]
    }
  ]
}
